{
  "gitSyncId": "644b91f6a9a0f069b4feaa24_645cd16ba68b7315a30b048f",
  "id": "Restaurant Partners_utils.updatePartner",
  "pluginId": "js-plugin",
  "pluginType": "JS",
  "unpublishedAction": {
    "actionConfiguration": {
      "encodeParamsToggle": true,
      "isAsync": true,
      "jsArguments": [],
      "paginationType": "NONE",
      "timeoutInMillisecond": 10000
    },
    "collectionId": "Restaurant Partners_utils",
    "confirmBeforeExecute": false,
    "datasource": {
      "isAutoGenerated": false,
      "name": "UNUSED_DATASOURCE",
      "pluginId": "js-plugin"
    },
    "dynamicBindingPathList": [
      {
        "key": "body"
      }
    ],
    "executeOnLoad": false,
    "fullyQualifiedName": "utils.updatePartner",
    "name": "updatePartner",
    "pageId": "Restaurant Partners",
    "userSetOnLoad": false
  }
}